asciify/__init__.py
asciify/algo.py
asciify/cli.py
asciify/courier.ttf
asciify_it-1.1.0.dist-info/LICENSE
asciify_it-1.1.0.dist-info/METADATA
asciify_it-1.1.0.dist-info/WHEEL
asciify_it-1.1.0.dist-info/entry_points.txt
asciify_it-1.1.0.dist-info/top_level.txt
asciify_it-1.1.0.dist-info/RECORD
