Metadata-Version: 2.1
Name: asciify-it
Version: 1.1.0
Summary: Convert your images to awesome ASCII arts!
Home-page: https://gitlab.com/Mathematician2000/ascii-art
Author: AArtur & Mathematician2000
Author-email: asciify@mail.ru
License: MIT License
Project-URL: Documentation, https://ascii-art.readthedocs.io/en/latest
Keywords: ASCII,images,CLI
Classifier: Programming Language :: Python :: 3
Classifier: Environment :: Console
Classifier: Operating System :: OS Independent
Classifier: Topic :: Scientific/Engineering :: Image Processing
Requires-Python: >=3.7
License-File: LICENSE
Requires-Dist: click
Requires-Dist: nptyping
Requires-Dist: numba
Requires-Dist: numpy
Requires-Dist: Pillow
Requires-Dist: scipy
Requires-Dist: tqdm
